kodo/broadcast.py
kodo_broadcast-0.2.0.dist-info/licenses/LICENSE.txt
kodo_broadcast-0.2.0.dist-info/WHEEL
kodo_broadcast-0.2.0.dist-info/METADATA
kodo_broadcast-0.2.0.dist-info/RECORD
