Metadata-Version: 2.4
Name: kodo.broadcast
Version: 0.2.0
Summary: Pythonic, asynchronous multi-endpoint object delivery
Author-email: Dom Sekotill <dom.sekotill@kodo.org.uk>
Requires-Python: ~=3.12
License-File: LICENSE.txt
Requires-Dist: anyio ~=4.0
Requires-Dist: pytest-timeout ; extra == "test"
Requires-Dist: pytest-trio ; extra == "test"
Requires-Dist: trio ; extra == "trio"
Provides-Extra: test
Provides-Extra: trio
